{"metadata": {"dbt_schema_version": "https://schemas.getdbt.com/dbt/run-results/v4.json", "dbt_version": "1.4.5", "generated_at": "2023-05-17T19:35:44.738908Z", "invocation_id": "c726ae80-286e-486e-b5e1-9954e6b4123e", "env": {}}, "results": [{"status": "success", "timing": [{"name": "compile", "started_at": "2023-05-17T19:35:43.681876Z", "completed_at": "2023-05-17T19:35:43.688343Z"}, {"name": "execute", "started_at": "2023-05-17T19:35:43.693230Z", "completed_at": "2023-05-17T19:35:43.693233Z"}], "thread_id": "Thread-1", "execution_time": 0.01738286018371582, "adapter_response": {}, "message": null, "failures": null, "unique_id": "model.apple_search_ads_source.stg_apple_search_ads__ad_group_history_tmp"}, {"status": "success", "timing": [{"name": "compile", "started_at": "2023-05-17T19:35:43.678320Z", "completed_at": "2023-05-17T19:35:43.685151Z"}, {"name": "execute", "started_at": "2023-05-17T19:35:43.693098Z", "completed_at": "2023-05-17T19:35:43.693110Z"}], "thread_id": "Thread-2", "execution_time": 0.018264055252075195, "adapter_response": {}, "message": null, "failures": null, "unique_id": "model.apple_search_ads_source.stg_apple_search_ads__ad_group_report_tmp"}, {"status": "success", "timing": [{"name": "compile", "started_at": "2023-05-17T19:35:43.685341Z", "completed_at": "2023-05-17T19:35:43.692819Z"}, {"name": "execute", "started_at": "2023-05-17T19:35:43.696831Z", "completed_at": "2023-05-17T19:35:43.696838Z"}], "thread_id": "Thread-3", "execution_time": 0.021008968353271484, "adapter_response": {}, "message": null, "failures": null, "unique_id": "model.apple_search_ads_source.stg_apple_search_ads__ad_history_tmp"}, {"status": "success", "timing": [{"name": "compile", "started_at": "2023-05-17T19:35:43.688641Z", "completed_at": "2023-05-17T19:35:43.695046Z"}, {"name": "execute", "started_at": "2023-05-17T19:35:43.697466Z", "completed_at": "2023-05-17T19:35:43.697473Z"}], "thread_id": "Thread-4", "execution_time": 0.021212100982666016, "adapter_response": {}, "message": null, "failures": null, "unique_id": "model.apple_search_ads_source.stg_apple_search_ads__ad_report_tmp"}, {"status": "success", "timing": [{"name": "compile", "started_at": "2023-05-17T19:35:43.698952Z", "completed_at": "2023-05-17T19:35:43.705480Z"}, {"name": "execute", "started_at": "2023-05-17T19:35:43.711205Z", "completed_at": "2023-05-17T19:35:43.711212Z"}], "thread_id": "Thread-1", "execution_time": 0.015243053436279297, "adapter_response": {}, "message": null, "failures": null, "unique_id": "model.apple_search_ads_source.stg_apple_search_ads__campaign_history_tmp"}, {"status": "success", "timing": [{"name": "compile", "started_at": "2023-05-17T19:35:43.701832Z", "completed_at": "2023-05-17T19:35:43.705730Z"}, {"name": "execute", "started_at": "2023-05-17T19:35:43.711375Z", "completed_at": "2023-05-17T19:35:43.711378Z"}], "thread_id": "Thread-2", "execution_time": 0.01518106460571289, "adapter_response": {}, "message": null, "failures": null, "unique_id": "model.apple_search_ads_source.stg_apple_search_ads__campaign_report_tmp"}, {"status": "success", "timing": [{"name": "compile", "started_at": "2023-05-17T19:35:43.706082Z", "completed_at": "2023-05-17T19:35:43.711917Z"}, {"name": "execute", "started_at": "2023-05-17T19:35:43.713480Z", "completed_at": "2023-05-17T19:35:43.713484Z"}], "thread_id": "Thread-3", "execution_time": 0.009585142135620117, "adapter_response": {}, "message": null, "failures": null, "unique_id": "model.apple_search_ads_source.stg_apple_search_ads__keyword_history_tmp"}, {"status": "success", "timing": [{"name": "compile", "started_at": "2023-05-17T19:35:43.709220Z", "completed_at": "2023-05-17T19:35:43.712537Z"}, {"name": "execute", "started_at": "2023-05-17T19:35:43.713959Z", "completed_at": "2023-05-17T19:35:43.713962Z"}], "thread_id": "Thread-4", "execution_time": 0.01175689697265625, "adapter_response": {}, "message": null, "failures": null, "unique_id": "model.apple_search_ads_source.stg_apple_search_ads__keyword_report_tmp"}, {"status": "success", "timing": [{"name": "compile", "started_at": "2023-05-17T19:35:43.714450Z", "completed_at": "2023-05-17T19:35:43.721118Z"}, {"name": "execute", "started_at": "2023-05-17T19:35:43.723441Z", "completed_at": "2023-05-17T19:35:43.723446Z"}], "thread_id": "Thread-1", "execution_time": 0.01194000244140625, "adapter_response": {}, "message": null, "failures": null, "unique_id": "model.apple_search_ads_source.stg_apple_search_ads__organization_tmp"}, {"status": "success", "timing": [{"name": "compile", "started_at": "2023-05-17T19:35:43.717306Z", "completed_at": "2023-05-17T19:35:43.721715Z"}, {"name": "execute", "started_at": "2023-05-17T19:35:43.724677Z", "completed_at": "2023-05-17T19:35:43.724682Z"}], "thread_id": "Thread-2", "execution_time": 0.011990070343017578, "adapter_response": {}, "message": null, "failures": null, "unique_id": "model.apple_search_ads_source.stg_apple_search_ads__search_term_report_tmp"}, {"status": "success", "timing": [{"name": "compile", "started_at": "2023-05-17T19:35:43.722247Z", "completed_at": "2023-05-17T19:35:43.723159Z"}, {"name": "execute", "started_at": "2023-05-17T19:35:43.725303Z", "completed_at": "2023-05-17T19:35:43.725307Z"}], "thread_id": "Thread-3", "execution_time": 0.005357027053833008, "adapter_response": {}, "message": null, "failures": null, "unique_id": "seed.apple_search_ads_source_integration_tests.ad_group_history_data"}, {"status": "success", "timing": [{"name": "compile", "started_at": "2023-05-17T19:35:43.723561Z", "completed_at": "2023-05-17T19:35:43.724358Z"}, {"name": "execute", "started_at": "2023-05-17T19:35:43.725964Z", "completed_at": "2023-05-17T19:35:43.725967Z"}], "thread_id": "Thread-4", "execution_time": 0.005738019943237305, "adapter_response": {}, "message": null, "failures": null, "unique_id": "seed.apple_search_ads_source_integration_tests.ad_group_report_data"}, {"status": "success", "timing": [{"name": "compile", "started_at": "2023-05-17T19:35:43.728211Z", "completed_at": "2023-05-17T19:35:43.729155Z"}, {"name": "execute", "started_at": "2023-05-17T19:35:43.732539Z", "completed_at": "2023-05-17T19:35:43.732544Z"}], "thread_id": "Thread-1", "execution_time": 0.00741887092590332, "adapter_response": {}, "message": null, "failures": null, "unique_id": "seed.apple_search_ads_source_integration_tests.ad_history_data"}, {"status": "success", "timing": [{"name": "compile", "started_at": "2023-05-17T19:35:43.729651Z", "completed_at": "2023-05-17T19:35:43.731168Z"}, {"name": "execute", "started_at": "2023-05-17T19:35:43.733721Z", "completed_at": "2023-05-17T19:35:43.733726Z"}], "thread_id": "Thread-2", "execution_time": 0.00718998908996582, "adapter_response": {}, "message": null, "failures": null, "unique_id": "seed.apple_search_ads_source_integration_tests.ad_report_data"}, {"status": "success", "timing": [{"name": "compile", "started_at": "2023-05-17T19:35:43.731554Z", "completed_at": "2023-05-17T19:35:43.732303Z"}, {"name": "execute", "started_at": "2023-05-17T19:35:43.734280Z", "completed_at": "2023-05-17T19:35:43.734283Z"}], "thread_id": "Thread-3", "execution_time": 0.007245063781738281, "adapter_response": {}, "message": null, "failures": null, "unique_id": "seed.apple_search_ads_source_integration_tests.campaign_history_data"}, {"status": "success", "timing": [{"name": "compile", "started_at": "2023-05-17T19:35:43.732662Z", "completed_at": "2023-05-17T19:35:43.733465Z"}, {"name": "execute", "started_at": "2023-05-17T19:35:43.734854Z", "completed_at": "2023-05-17T19:35:43.734857Z"}], "thread_id": "Thread-4", "execution_time": 0.006498098373413086, "adapter_response": {}, "message": null, "failures": null, "unique_id": "seed.apple_search_ads_source_integration_tests.campaign_report_data"}, {"status": "success", "timing": [{"name": "compile", "started_at": "2023-05-17T19:35:43.736929Z", "completed_at": "2023-05-17T19:35:43.737771Z"}, {"name": "execute", "started_at": "2023-05-17T19:35:43.740274Z", "completed_at": "2023-05-17T19:35:43.740277Z"}], "thread_id": "Thread-1", "execution_time": 0.006227970123291016, "adapter_response": {}, "message": null, "failures": null, "unique_id": "seed.apple_search_ads_source_integration_tests.keyword_history_data"}, {"status": "success", "timing": [{"name": "compile", "started_at": "2023-05-17T19:35:43.738239Z", "completed_at": "2023-05-17T19:35:43.739014Z"}, {"name": "execute", "started_at": "2023-05-17T19:35:43.741355Z", "completed_at": "2023-05-17T19:35:43.741359Z"}], "thread_id": "Thread-2", "execution_time": 0.006030082702636719, "adapter_response": {}, "message": null, "failures": null, "unique_id": "seed.apple_search_ads_source_integration_tests.keyword_report_data"}, {"status": "success", "timing": [{"name": "compile", "started_at": "2023-05-17T19:35:43.739333Z", "completed_at": "2023-05-17T19:35:43.740057Z"}, {"name": "execute", "started_at": "2023-05-17T19:35:43.741853Z", "completed_at": "2023-05-17T19:35:43.741856Z"}], "thread_id": "Thread-3", "execution_time": 0.006051778793334961, "adapter_response": {}, "message": null, "failures": null, "unique_id": "seed.apple_search_ads_source_integration_tests.organization_data"}, {"status": "success", "timing": [{"name": "compile", "started_at": "2023-05-17T19:35:43.740407Z", "completed_at": "2023-05-17T19:35:43.741136Z"}, {"name": "execute", "started_at": "2023-05-17T19:35:43.742353Z", "completed_at": "2023-05-17T19:35:43.742356Z"}], "thread_id": "Thread-4", "execution_time": 0.005400180816650391, "adapter_response": {}, "message": null, "failures": null, "unique_id": "seed.apple_search_ads_source_integration_tests.search_term_report_data"}, {"status": "success", "timing": [{"name": "compile", "started_at": "2023-05-17T19:35:43.745211Z", "completed_at": "2023-05-17T19:35:44.049733Z"}, {"name": "execute", "started_at": "2023-05-17T19:35:44.051393Z", "completed_at": "2023-05-17T19:35:44.051401Z"}], "thread_id": "Thread-1", "execution_time": 0.33281588554382324, "adapter_response": {}, "message": null, "failures": null, "unique_id": "model.apple_search_ads_source.stg_apple_search_ads__ad_group_history"}, {"status": "success", "timing": [{"name": "compile", "started_at": "2023-05-17T19:35:43.754724Z", "completed_at": "2023-05-17T19:35:44.050683Z"}, {"name": "execute", "started_at": "2023-05-17T19:35:44.051644Z", "completed_at": "2023-05-17T19:35:44.051648Z"}], "thread_id": "Thread-3", "execution_time": 0.331251859664917, "adapter_response": {}, "message": null, "failures": null, "unique_id": "model.apple_search_ads_source.stg_apple_search_ads__ad_history"}, {"status": "success", "timing": [{"name": "compile", "started_at": "2023-05-17T19:35:43.751146Z", "completed_at": "2023-05-17T19:35:44.051515Z"}, {"name": "execute", "started_at": "2023-05-17T19:35:44.052300Z", "completed_at": "2023-05-17T19:35:44.052304Z"}], "thread_id": "Thread-2", "execution_time": 0.36849427223205566, "adapter_response": {}, "message": null, "failures": null, "unique_id": "model.apple_search_ads_source.stg_apple_search_ads__ad_group_report"}, {"status": "success", "timing": [{"name": "compile", "started_at": "2023-05-17T19:35:43.758122Z", "completed_at": "2023-05-17T19:35:44.051723Z"}, {"name": "execute", "started_at": "2023-05-17T19:35:44.052439Z", "completed_at": "2023-05-17T19:35:44.052442Z"}], "thread_id": "Thread-4", "execution_time": 0.3616459369659424, "adapter_response": {}, "message": null, "failures": null, "unique_id": "model.apple_search_ads_source.stg_apple_search_ads__ad_report"}, {"status": "success", "timing": [{"name": "compile", "started_at": "2023-05-17T19:35:44.117845Z", "completed_at": "2023-05-17T19:35:44.369496Z"}, {"name": "execute", "started_at": "2023-05-17T19:35:44.369749Z", "completed_at": "2023-05-17T19:35:44.369756Z"}], "thread_id": "Thread-4", "execution_time": 0.2803168296813965, "adapter_response": {}, "message": null, "failures": null, "unique_id": "model.apple_search_ads_source.stg_apple_search_ads__keyword_report"}, {"status": "success", "timing": [{"name": "compile", "started_at": "2023-05-17T19:35:44.077562Z", "completed_at": "2023-05-17T19:35:44.383065Z"}, {"name": "execute", "started_at": "2023-05-17T19:35:44.383462Z", "completed_at": "2023-05-17T19:35:44.383466Z"}], "thread_id": "Thread-1", "execution_time": 0.3301272392272949, "adapter_response": {}, "message": null, "failures": null, "unique_id": "model.apple_search_ads_source.stg_apple_search_ads__campaign_history"}, {"status": "success", "timing": [{"name": "compile", "started_at": "2023-05-17T19:35:44.081790Z", "completed_at": "2023-05-17T19:35:44.382623Z"}, {"name": "execute", "started_at": "2023-05-17T19:35:44.382962Z", "completed_at": "2023-05-17T19:35:44.382968Z"}], "thread_id": "Thread-3", "execution_time": 0.33016204833984375, "adapter_response": {}, "message": null, "failures": null, "unique_id": "model.apple_search_ads_source.stg_apple_search_ads__campaign_report"}, {"status": "success", "timing": [{"name": "compile", "started_at": "2023-05-17T19:35:44.412740Z", "completed_at": "2023-05-17T19:35:44.420970Z"}, {"name": "execute", "started_at": "2023-05-17T19:35:44.421207Z", "completed_at": "2023-05-17T19:35:44.421213Z"}], "thread_id": "Thread-3", "execution_time": 0.013156890869140625, "adapter_response": {}, "message": null, "failures": null, "unique_id": "test.apple_search_ads_source.dbt_utils_unique_combination_of_columns_stg_apple_search_ads__ad_group_history_ad_group_id__modified_at.84af14c83b"}, {"status": "success", "timing": [{"name": "compile", "started_at": "2023-05-17T19:35:44.422178Z", "completed_at": "2023-05-17T19:35:44.427171Z"}, {"name": "execute", "started_at": "2023-05-17T19:35:44.427405Z", "completed_at": "2023-05-17T19:35:44.427409Z"}], "thread_id": "Thread-3", "execution_time": 0.005888938903808594, "adapter_response": {}, "message": null, "failures": null, "unique_id": "test.apple_search_ads_source.not_null_stg_apple_search_ads__ad_group_history_ad_group_id.dc128eecb7"}, {"status": "success", "timing": [{"name": "compile", "started_at": "2023-05-17T19:35:44.428351Z", "completed_at": "2023-05-17T19:35:44.430837Z"}, {"name": "execute", "started_at": "2023-05-17T19:35:44.431064Z", "completed_at": "2023-05-17T19:35:44.431068Z"}], "thread_id": "Thread-3", "execution_time": 0.0033130645751953125, "adapter_response": {}, "message": null, "failures": null, "unique_id": "test.apple_search_ads_source.not_null_stg_apple_search_ads__ad_group_history_modified_at.e5d65fa28f"}, {"status": "success", "timing": [{"name": "compile", "started_at": "2023-05-17T19:35:44.114333Z", "completed_at": "2023-05-17T19:35:44.405285Z"}, {"name": "execute", "started_at": "2023-05-17T19:35:44.405547Z", "completed_at": "2023-05-17T19:35:44.405553Z"}], "thread_id": "Thread-2", "execution_time": 0.32192301750183105, "adapter_response": {}, "message": null, "failures": null, "unique_id": "model.apple_search_ads_source.stg_apple_search_ads__keyword_history"}, {"status": "success", "timing": [{"name": "compile", "started_at": "2023-05-17T19:35:44.431980Z", "completed_at": "2023-05-17T19:35:44.435111Z"}, {"name": "execute", "started_at": "2023-05-17T19:35:44.435900Z", "completed_at": "2023-05-17T19:35:44.435904Z"}], "thread_id": "Thread-3", "execution_time": 0.004783153533935547, "adapter_response": {}, "message": null, "failures": null, "unique_id": "test.apple_search_ads_source.dbt_utils_unique_combination_of_columns_stg_apple_search_ads__ad_history_ad_id__modified_at.38599b8cba"}, {"status": "success", "timing": [{"name": "compile", "started_at": "2023-05-17T19:35:44.436861Z", "completed_at": "2023-05-17T19:35:44.442636Z"}, {"name": "execute", "started_at": "2023-05-17T19:35:44.442897Z", "completed_at": "2023-05-17T19:35:44.442901Z"}], "thread_id": "Thread-2", "execution_time": 0.007158994674682617, "adapter_response": {}, "message": null, "failures": null, "unique_id": "test.apple_search_ads_source.not_null_stg_apple_search_ads__ad_history_ad_id.4ad3bde32a"}, {"status": "success", "timing": [{"name": "compile", "started_at": "2023-05-17T19:35:44.439691Z", "completed_at": "2023-05-17T19:35:44.443437Z"}, {"name": "execute", "started_at": "2023-05-17T19:35:44.444091Z", "completed_at": "2023-05-17T19:35:44.444095Z"}], "thread_id": "Thread-3", "execution_time": 0.00801706314086914, "adapter_response": {}, "message": null, "failures": null, "unique_id": "test.apple_search_ads_source.not_null_stg_apple_search_ads__ad_history_modified_at.2eea7e006d"}, {"status": "success", "timing": [{"name": "compile", "started_at": "2023-05-17T19:35:44.444194Z", "completed_at": "2023-05-17T19:35:44.448079Z"}, {"name": "execute", "started_at": "2023-05-17T19:35:44.451754Z", "completed_at": "2023-05-17T19:35:44.451762Z"}], "thread_id": "Thread-2", "execution_time": 0.00852203369140625, "adapter_response": {}, "message": null, "failures": null, "unique_id": "test.apple_search_ads_source.dbt_utils_unique_combination_of_columns_stg_apple_search_ads__ad_group_report_ad_group_id__date_day.a0fcc4e33c"}, {"status": "success", "timing": [{"name": "compile", "started_at": "2023-05-17T19:35:44.448251Z", "completed_at": "2023-05-17T19:35:44.452410Z"}, {"name": "execute", "started_at": "2023-05-17T19:35:44.453096Z", "completed_at": "2023-05-17T19:35:44.453099Z"}], "thread_id": "Thread-3", "execution_time": 0.008337974548339844, "adapter_response": {}, "message": null, "failures": null, "unique_id": "test.apple_search_ads_source.dbt_utils_unique_combination_of_columns_stg_apple_search_ads__ad_report_ad_id__date_day__ad_group_id.0d8d23c516"}, {"status": "success", "timing": [{"name": "compile", "started_at": "2023-05-17T19:35:44.453201Z", "completed_at": "2023-05-17T19:35:44.456873Z"}, {"name": "execute", "started_at": "2023-05-17T19:35:44.459580Z", "completed_at": "2023-05-17T19:35:44.459585Z"}], "thread_id": "Thread-2", "execution_time": 0.007313251495361328, "adapter_response": {}, "message": null, "failures": null, "unique_id": "test.apple_search_ads_source.not_null_stg_apple_search_ads__ad_group_report_ad_group_id.a115f9cfc1"}, {"status": "success", "timing": [{"name": "compile", "started_at": "2023-05-17T19:35:44.456985Z", "completed_at": "2023-05-17T19:35:44.460165Z"}, {"name": "execute", "started_at": "2023-05-17T19:35:44.460824Z", "completed_at": "2023-05-17T19:35:44.460828Z"}], "thread_id": "Thread-3", "execution_time": 0.00713801383972168, "adapter_response": {}, "message": null, "failures": null, "unique_id": "test.apple_search_ads_source.not_null_stg_apple_search_ads__ad_group_report_date_day.4dfd46a43b"}, {"status": "success", "timing": [{"name": "compile", "started_at": "2023-05-17T19:35:44.460927Z", "completed_at": "2023-05-17T19:35:44.464605Z"}, {"name": "execute", "started_at": "2023-05-17T19:35:44.468134Z", "completed_at": "2023-05-17T19:35:44.468139Z"}], "thread_id": "Thread-2", "execution_time": 0.008112907409667969, "adapter_response": {}, "message": null, "failures": null, "unique_id": "test.apple_search_ads_source.not_null_stg_apple_search_ads__ad_report_ad_group_id.a397755e9f"}, {"status": "success", "timing": [{"name": "compile", "started_at": "2023-05-17T19:35:44.464725Z", "completed_at": "2023-05-17T19:35:44.468716Z"}, {"name": "execute", "started_at": "2023-05-17T19:35:44.469375Z", "completed_at": "2023-05-17T19:35:44.469379Z"}], "thread_id": "Thread-3", "execution_time": 0.007911920547485352, "adapter_response": {}, "message": null, "failures": null, "unique_id": "test.apple_search_ads_source.not_null_stg_apple_search_ads__ad_report_ad_id.d08e760c58"}, {"status": "success", "timing": [{"name": "compile", "started_at": "2023-05-17T19:35:44.469477Z", "completed_at": "2023-05-17T19:35:44.472871Z"}, {"name": "execute", "started_at": "2023-05-17T19:35:44.476116Z", "completed_at": "2023-05-17T19:35:44.476120Z"}], "thread_id": "Thread-2", "execution_time": 0.007547855377197266, "adapter_response": {}, "message": null, "failures": null, "unique_id": "test.apple_search_ads_source.not_null_stg_apple_search_ads__ad_report_date_day.e6252346d8"}, {"status": "success", "timing": [{"name": "compile", "started_at": "2023-05-17T19:35:44.472985Z", "completed_at": "2023-05-17T19:35:44.476704Z"}, {"name": "execute", "started_at": "2023-05-17T19:35:44.477365Z", "completed_at": "2023-05-17T19:35:44.477369Z"}], "thread_id": "Thread-3", "execution_time": 0.00758814811706543, "adapter_response": {}, "message": null, "failures": null, "unique_id": "test.apple_search_ads_source.dbt_utils_unique_combination_of_columns_stg_apple_search_ads__keyword_report_keyword_id__date_day.9f0099cff8"}, {"status": "success", "timing": [{"name": "compile", "started_at": "2023-05-17T19:35:44.477473Z", "completed_at": "2023-05-17T19:35:44.480862Z"}, {"name": "execute", "started_at": "2023-05-17T19:35:44.483549Z", "completed_at": "2023-05-17T19:35:44.483554Z"}], "thread_id": "Thread-2", "execution_time": 0.006994962692260742, "adapter_response": {}, "message": null, "failures": null, "unique_id": "test.apple_search_ads_source.not_null_stg_apple_search_ads__keyword_report_date_day.16098db928"}, {"status": "success", "timing": [{"name": "compile", "started_at": "2023-05-17T19:35:44.480964Z", "completed_at": "2023-05-17T19:35:44.484149Z"}, {"name": "execute", "started_at": "2023-05-17T19:35:44.484738Z", "completed_at": "2023-05-17T19:35:44.484742Z"}], "thread_id": "Thread-3", "execution_time": 0.0073699951171875, "adapter_response": {}, "message": null, "failures": null, "unique_id": "test.apple_search_ads_source.not_null_stg_apple_search_ads__keyword_report_keyword_id.501725b09e"}, {"status": "success", "timing": [{"name": "compile", "started_at": "2023-05-17T19:35:44.484858Z", "completed_at": "2023-05-17T19:35:44.488503Z"}, {"name": "execute", "started_at": "2023-05-17T19:35:44.491866Z", "completed_at": "2023-05-17T19:35:44.491871Z"}], "thread_id": "Thread-2", "execution_time": 0.00793910026550293, "adapter_response": {}, "message": null, "failures": null, "unique_id": "test.apple_search_ads_source.dbt_utils_unique_combination_of_columns_stg_apple_search_ads__campaign_history_campaign_id__modified_at.317f970af9"}, {"status": "success", "timing": [{"name": "compile", "started_at": "2023-05-17T19:35:44.488816Z", "completed_at": "2023-05-17T19:35:44.492754Z"}, {"name": "execute", "started_at": "2023-05-17T19:35:44.495542Z", "completed_at": "2023-05-17T19:35:44.495547Z"}], "thread_id": "Thread-3", "execution_time": 0.007606029510498047, "adapter_response": {}, "message": null, "failures": null, "unique_id": "test.apple_search_ads_source.not_null_stg_apple_search_ads__campaign_history_campaign_id.3f0f7502b8"}, {"status": "success", "timing": [{"name": "compile", "started_at": "2023-05-17T19:35:44.493113Z", "completed_at": "2023-05-17T19:35:44.496223Z"}, {"name": "execute", "started_at": "2023-05-17T19:35:44.496855Z", "completed_at": "2023-05-17T19:35:44.496859Z"}], "thread_id": "Thread-2", "execution_time": 0.007690906524658203, "adapter_response": {}, "message": null, "failures": null, "unique_id": "test.apple_search_ads_source.not_null_stg_apple_search_ads__campaign_history_modified_at.f34a7a97c9"}, {"status": "success", "timing": [{"name": "compile", "started_at": "2023-05-17T19:35:44.496968Z", "completed_at": "2023-05-17T19:35:44.501032Z"}, {"name": "execute", "started_at": "2023-05-17T19:35:44.503874Z", "completed_at": "2023-05-17T19:35:44.503880Z"}], "thread_id": "Thread-3", "execution_time": 0.007877826690673828, "adapter_response": {}, "message": null, "failures": null, "unique_id": "test.apple_search_ads_source.dbt_utils_unique_combination_of_columns_stg_apple_search_ads__campaign_report_campaign_id__date_day.bad41b0481"}, {"status": "success", "timing": [{"name": "compile", "started_at": "2023-05-17T19:35:44.501138Z", "completed_at": "2023-05-17T19:35:44.504525Z"}, {"name": "execute", "started_at": "2023-05-17T19:35:44.505187Z", "completed_at": "2023-05-17T19:35:44.505192Z"}], "thread_id": "Thread-2", "execution_time": 0.0073699951171875, "adapter_response": {}, "message": null, "failures": null, "unique_id": "test.apple_search_ads_source.not_null_stg_apple_search_ads__campaign_report_campaign_id.b83941e728"}, {"status": "success", "timing": [{"name": "compile", "started_at": "2023-05-17T19:35:44.505313Z", "completed_at": "2023-05-17T19:35:44.508708Z"}, {"name": "execute", "started_at": "2023-05-17T19:35:44.512372Z", "completed_at": "2023-05-17T19:35:44.512377Z"}], "thread_id": "Thread-3", "execution_time": 0.00806570053100586, "adapter_response": {}, "message": null, "failures": null, "unique_id": "test.apple_search_ads_source.not_null_stg_apple_search_ads__campaign_report_date_day.c8dc10a6f3"}, {"status": "success", "timing": [{"name": "compile", "started_at": "2023-05-17T19:35:44.509272Z", "completed_at": "2023-05-17T19:35:44.513469Z"}, {"name": "execute", "started_at": "2023-05-17T19:35:44.517080Z", "completed_at": "2023-05-17T19:35:44.517088Z"}], "thread_id": "Thread-2", "execution_time": 0.008989095687866211, "adapter_response": {}, "message": null, "failures": null, "unique_id": "test.apple_search_ads_source.dbt_utils_unique_combination_of_columns_stg_apple_search_ads__keyword_history_keyword_id__modified_at.7b06162d24"}, {"status": "success", "timing": [{"name": "compile", "started_at": "2023-05-17T19:35:44.513580Z", "completed_at": "2023-05-17T19:35:44.517649Z"}, {"name": "execute", "started_at": "2023-05-17T19:35:44.518328Z", "completed_at": "2023-05-17T19:35:44.518333Z"}], "thread_id": "Thread-3", "execution_time": 0.005613088607788086, "adapter_response": {}, "message": null, "failures": null, "unique_id": "test.apple_search_ads_source.not_null_stg_apple_search_ads__keyword_history_keyword_id.889f83cfd2"}, {"status": "success", "timing": [{"name": "compile", "started_at": "2023-05-17T19:35:44.518865Z", "completed_at": "2023-05-17T19:35:44.521458Z"}, {"name": "execute", "started_at": "2023-05-17T19:35:44.521720Z", "completed_at": "2023-05-17T19:35:44.521725Z"}], "thread_id": "Thread-2", "execution_time": 0.003924131393432617, "adapter_response": {}, "message": null, "failures": null, "unique_id": "test.apple_search_ads_source.not_null_stg_apple_search_ads__keyword_history_modified_at.42fde5a287"}, {"status": "success", "timing": [{"name": "compile", "started_at": "2023-05-17T19:35:44.395012Z", "completed_at": "2023-05-17T19:35:44.656030Z"}, {"name": "execute", "started_at": "2023-05-17T19:35:44.656297Z", "completed_at": "2023-05-17T19:35:44.656306Z"}], "thread_id": "Thread-4", "execution_time": 0.2957890033721924, "adapter_response": {}, "message": null, "failures": null, "unique_id": "model.apple_search_ads_source.stg_apple_search_ads__organization"}, {"status": "success", "timing": [{"name": "compile", "started_at": "2023-05-17T19:35:44.692098Z", "completed_at": "2023-05-17T19:35:44.697977Z"}, {"name": "execute", "started_at": "2023-05-17T19:35:44.698454Z", "completed_at": "2023-05-17T19:35:44.698458Z"}], "thread_id": "Thread-3", "execution_time": 0.007723093032836914, "adapter_response": {}, "message": null, "failures": null, "unique_id": "test.apple_search_ads_source.dbt_utils_unique_combination_of_columns_stg_apple_search_ads__organization_organization_id.8647048f7a"}, {"status": "success", "timing": [{"name": "compile", "started_at": "2023-05-17T19:35:44.695540Z", "completed_at": "2023-05-17T19:35:44.698549Z"}, {"name": "execute", "started_at": "2023-05-17T19:35:44.699203Z", "completed_at": "2023-05-17T19:35:44.699207Z"}], "thread_id": "Thread-2", "execution_time": 0.0076520442962646484, "adapter_response": {}, "message": null, "failures": null, "unique_id": "test.apple_search_ads_source.not_null_stg_apple_search_ads__organization_organization_id.b013ce33cb"}, {"status": "success", "timing": [{"name": "compile", "started_at": "2023-05-17T19:35:44.408861Z", "completed_at": "2023-05-17T19:35:44.691692Z"}, {"name": "execute", "started_at": "2023-05-17T19:35:44.695370Z", "completed_at": "2023-05-17T19:35:44.695376Z"}], "thread_id": "Thread-1", "execution_time": 0.31641578674316406, "adapter_response": {}, "message": null, "failures": null, "unique_id": "model.apple_search_ads_source.stg_apple_search_ads__search_term_report"}, {"status": "success", "timing": [{"name": "compile", "started_at": "2023-05-17T19:35:44.726462Z", "completed_at": "2023-05-17T19:35:44.735786Z"}, {"name": "execute", "started_at": "2023-05-17T19:35:44.736452Z", "completed_at": "2023-05-17T19:35:44.736458Z"}], "thread_id": "Thread-4", "execution_time": 0.011868953704833984, "adapter_response": {}, "message": null, "failures": null, "unique_id": "test.apple_search_ads_source.dbt_utils_unique_combination_of_columns_stg_apple_search_ads__search_term_report__fivetran_id__date_day.aad2a48344"}, {"status": "success", "timing": [{"name": "compile", "started_at": "2023-05-17T19:35:44.730032Z", "completed_at": "2023-05-17T19:35:44.735981Z"}, {"name": "execute", "started_at": "2023-05-17T19:35:44.736666Z", "completed_at": "2023-05-17T19:35:44.736669Z"}], "thread_id": "Thread-3", "execution_time": 0.011480093002319336, "adapter_response": {}, "message": null, "failures": null, "unique_id": "test.apple_search_ads_source.not_null_stg_apple_search_ads__search_term_report__fivetran_id.aa430d1dad"}, {"status": "success", "timing": [{"name": "compile", "started_at": "2023-05-17T19:35:44.733264Z", "completed_at": "2023-05-17T19:35:44.736244Z"}, {"name": "execute", "started_at": "2023-05-17T19:35:44.737128Z", "completed_at": "2023-05-17T19:35:44.737131Z"}], "thread_id": "Thread-2", "execution_time": 0.01158285140991211, "adapter_response": {}, "message": null, "failures": null, "unique_id": "test.apple_search_ads_source.not_null_stg_apple_search_ads__search_term_report_date_day.fd93df3302"}], "elapsed_time": 1.9605622291564941, "args": {"write_json": true, "use_colors": true, "printer_width": 80, "version_check": true, "partial_parse": true, "static_parser": true, "profiles_dir": "/Users/joseph.markiewicz/.dbt", "send_anonymous_usage_stats": true, "quiet": false, "no_print": false, "cache_selected_only": false, "target": "postgres", "compile": true, "which": "generate", "rpc_method": "docs.generate", "indirect_selection": "eager"}}