{"metadata": {"dbt_schema_version": "https://schemas.getdbt.com/dbt/run-results/v4.json", "dbt_version": "1.5.2", "generated_at": "2023-08-30T21:24:57.937590Z", "invocation_id": "26115620-823b-48d4-8f44-887ba02bc8fa", "env": {}}, "results": [{"status": "success", "timing": [{"name": "compile", "started_at": "2023-08-30T21:24:56.383486Z", "completed_at": "2023-08-30T21:24:56.419848Z"}, {"name": "execute", "started_at": "2023-08-30T21:24:56.432796Z", "completed_at": "2023-08-30T21:24:56.432805Z"}], "thread_id": "Thread-1", "execution_time": 0.05583500862121582, "adapter_response": {}, "message": null, "failures": null, "unique_id": "model.apple_search_ads_source.stg_apple_search_ads__ad_group_history_tmp"}, {"status": "success", "timing": [{"name": "compile", "started_at": "2023-08-30T21:24:56.407333Z", "completed_at": "2023-08-30T21:24:56.425303Z"}, {"name": "execute", "started_at": "2023-08-30T21:24:56.433854Z", "completed_at": "2023-08-30T21:24:56.433857Z"}], "thread_id": "Thread-2", "execution_time": 0.05611991882324219, "adapter_response": {}, "message": null, "failures": null, "unique_id": "model.apple_search_ads_source.stg_apple_search_ads__ad_group_report_tmp"}, {"status": "success", "timing": [{"name": "compile", "started_at": "2023-08-30T21:24:56.411491Z", "completed_at": "2023-08-30T21:24:56.431563Z"}, {"name": "execute", "started_at": "2023-08-30T21:24:56.434869Z", "completed_at": "2023-08-30T21:24:56.434872Z"}], "thread_id": "Thread-3", "execution_time": 0.05556511878967285, "adapter_response": {}, "message": null, "failures": null, "unique_id": "model.apple_search_ads_source.stg_apple_search_ads__ad_history_tmp"}, {"status": "success", "timing": [{"name": "compile", "started_at": "2023-08-30T21:24:56.417012Z", "completed_at": "2023-08-30T21:24:56.431799Z"}, {"name": "execute", "started_at": "2023-08-30T21:24:56.435308Z", "completed_at": "2023-08-30T21:24:56.435312Z"}], "thread_id": "Thread-5", "execution_time": 0.05508303642272949, "adapter_response": {}, "message": null, "failures": null, "unique_id": "model.apple_search_ads_source.stg_apple_search_ads__campaign_history_tmp"}, {"status": "success", "timing": [{"name": "compile", "started_at": "2023-08-30T21:24:56.420109Z", "completed_at": "2023-08-30T21:24:56.432292Z"}, {"name": "execute", "started_at": "2023-08-30T21:24:56.436157Z", "completed_at": "2023-08-30T21:24:56.436160Z"}], "thread_id": "Thread-6", "execution_time": 0.055480003356933594, "adapter_response": {}, "message": null, "failures": null, "unique_id": "model.apple_search_ads_source.stg_apple_search_ads__campaign_report_tmp"}, {"status": "success", "timing": [{"name": "compile", "started_at": "2023-08-30T21:24:56.422667Z", "completed_at": "2023-08-30T21:24:56.432583Z"}, {"name": "execute", "started_at": "2023-08-30T21:24:56.436369Z", "completed_at": "2023-08-30T21:24:56.436373Z"}], "thread_id": "Thread-7", "execution_time": 0.04279184341430664, "adapter_response": {}, "message": null, "failures": null, "unique_id": "model.apple_search_ads_source.stg_apple_search_ads__keyword_history_tmp"}, {"status": "success", "timing": [{"name": "compile", "started_at": "2023-08-30T21:24:56.414208Z", "completed_at": "2023-08-30T21:24:56.433278Z"}, {"name": "execute", "started_at": "2023-08-30T21:24:56.437270Z", "completed_at": "2023-08-30T21:24:56.437274Z"}], "thread_id": "Thread-4", "execution_time": 0.05795407295227051, "adapter_response": {}, "message": null, "failures": null, "unique_id": "model.apple_search_ads_source.stg_apple_search_ads__ad_report_tmp"}, {"status": "success", "timing": [{"name": "compile", "started_at": "2023-08-30T21:24:56.425547Z", "completed_at": "2023-08-30T21:24:56.433640Z"}, {"name": "execute", "started_at": "2023-08-30T21:24:56.437900Z", "completed_at": "2023-08-30T21:24:56.437903Z"}], "thread_id": "Thread-8", "execution_time": 0.03395509719848633, "adapter_response": {}, "message": null, "failures": null, "unique_id": "model.apple_search_ads_source.stg_apple_search_ads__keyword_report_tmp"}, {"status": "success", "timing": [{"name": "compile", "started_at": "2023-08-30T21:24:56.452045Z", "completed_at": "2023-08-30T21:24:56.452925Z"}, {"name": "execute", "started_at": "2023-08-30T21:24:56.461241Z", "completed_at": "2023-08-30T21:24:56.461248Z"}], "thread_id": "Thread-3", "execution_time": 0.021458148956298828, "adapter_response": {}, "message": null, "failures": null, "unique_id": "seed.apple_search_ads_source_integration_tests.ad_group_history_data"}, {"status": "success", "timing": [{"name": "compile", "started_at": "2023-08-30T21:24:56.453372Z", "completed_at": "2023-08-30T21:24:56.454174Z"}, {"name": "execute", "started_at": "2023-08-30T21:24:56.461833Z", "completed_at": "2023-08-30T21:24:56.461837Z"}], "thread_id": "Thread-5", "execution_time": 0.02183222770690918, "adapter_response": {}, "message": null, "failures": null, "unique_id": "seed.apple_search_ads_source_integration_tests.ad_group_report_data"}, {"status": "success", "timing": [{"name": "compile", "started_at": "2023-08-30T21:24:56.443872Z", "completed_at": "2023-08-30T21:24:56.454537Z"}, {"name": "execute", "started_at": "2023-08-30T21:24:56.462215Z", "completed_at": "2023-08-30T21:24:56.462219Z"}], "thread_id": "Thread-1", "execution_time": 0.025662899017333984, "adapter_response": {}, "message": null, "failures": null, "unique_id": "model.apple_search_ads_source.stg_apple_search_ads__organization_tmp"}, {"status": "success", "timing": [{"name": "compile", "started_at": "2023-08-30T21:24:56.454804Z", "completed_at": "2023-08-30T21:24:56.455694Z"}, {"name": "execute", "started_at": "2023-08-30T21:24:56.462493Z", "completed_at": "2023-08-30T21:24:56.462496Z"}], "thread_id": "Thread-6", "execution_time": 0.022079944610595703, "adapter_response": {}, "message": null, "failures": null, "unique_id": "seed.apple_search_ads_source_integration_tests.ad_history_data"}, {"status": "success", "timing": [{"name": "compile", "started_at": "2023-08-30T21:24:56.455960Z", "completed_at": "2023-08-30T21:24:56.456826Z"}, {"name": "execute", "started_at": "2023-08-30T21:24:56.462722Z", "completed_at": "2023-08-30T21:24:56.462727Z"}], "thread_id": "Thread-7", "execution_time": 0.02215409278869629, "adapter_response": {}, "message": null, "failures": null, "unique_id": "seed.apple_search_ads_source_integration_tests.ad_report_data"}, {"status": "success", "timing": [{"name": "compile", "started_at": "2023-08-30T21:24:56.447939Z", "completed_at": "2023-08-30T21:24:56.457280Z"}, {"name": "execute", "started_at": "2023-08-30T21:24:56.463560Z", "completed_at": "2023-08-30T21:24:56.463563Z"}], "thread_id": "Thread-2", "execution_time": 0.025635957717895508, "adapter_response": {}, "message": null, "failures": null, "unique_id": "model.apple_search_ads_source.stg_apple_search_ads__search_term_report_tmp"}, {"status": "success", "timing": [{"name": "compile", "started_at": "2023-08-30T21:24:56.457503Z", "completed_at": "2023-08-30T21:24:56.459054Z"}, {"name": "execute", "started_at": "2023-08-30T21:24:56.463788Z", "completed_at": "2023-08-30T21:24:56.463792Z"}], "thread_id": "Thread-4", "execution_time": 0.019681930541992188, "adapter_response": {}, "message": null, "failures": null, "unique_id": "seed.apple_search_ads_source_integration_tests.campaign_history_data"}, {"status": "success", "timing": [{"name": "compile", "started_at": "2023-08-30T21:24:56.459485Z", "completed_at": "2023-08-30T21:24:56.460363Z"}, {"name": "execute", "started_at": "2023-08-30T21:24:56.464435Z", "completed_at": "2023-08-30T21:24:56.464438Z"}], "thread_id": "Thread-8", "execution_time": 0.019850969314575195, "adapter_response": {}, "message": null, "failures": null, "unique_id": "seed.apple_search_ads_source_integration_tests.campaign_report_data"}, {"status": "success", "timing": [{"name": "compile", "started_at": "2023-08-30T21:24:56.472433Z", "completed_at": "2023-08-30T21:24:56.473499Z"}, {"name": "execute", "started_at": "2023-08-30T21:24:56.496070Z", "completed_at": "2023-08-30T21:24:56.496076Z"}], "thread_id": "Thread-3", "execution_time": 0.02917194366455078, "adapter_response": {}, "message": null, "failures": null, "unique_id": "seed.apple_search_ads_source_integration_tests.keyword_history_data"}, {"status": "success", "timing": [{"name": "compile", "started_at": "2023-08-30T21:24:56.474079Z", "completed_at": "2023-08-30T21:24:56.474895Z"}, {"name": "execute", "started_at": "2023-08-30T21:24:56.496597Z", "completed_at": "2023-08-30T21:24:56.496600Z"}], "thread_id": "Thread-5", "execution_time": 0.029113054275512695, "adapter_response": {}, "message": null, "failures": null, "unique_id": "seed.apple_search_ads_source_integration_tests.keyword_report_data"}, {"status": "success", "timing": [{"name": "compile", "started_at": "2023-08-30T21:24:56.475295Z", "completed_at": "2023-08-30T21:24:56.476084Z"}, {"name": "execute", "started_at": "2023-08-30T21:24:56.496937Z", "completed_at": "2023-08-30T21:24:56.496939Z"}], "thread_id": "Thread-1", "execution_time": 0.029109954833984375, "adapter_response": {}, "message": null, "failures": null, "unique_id": "seed.apple_search_ads_source_integration_tests.organization_data"}, {"status": "success", "timing": [{"name": "compile", "started_at": "2023-08-30T21:24:56.476286Z", "completed_at": "2023-08-30T21:24:56.477070Z"}, {"name": "execute", "started_at": "2023-08-30T21:24:56.497120Z", "completed_at": "2023-08-30T21:24:56.497123Z"}], "thread_id": "Thread-6", "execution_time": 0.029204130172729492, "adapter_response": {}, "message": null, "failures": null, "unique_id": "seed.apple_search_ads_source_integration_tests.search_term_report_data"}, {"status": "success", "timing": [{"name": "compile", "started_at": "2023-08-30T21:24:56.488090Z", "completed_at": "2023-08-30T21:24:57.102638Z"}, {"name": "execute", "started_at": "2023-08-30T21:24:57.103218Z", "completed_at": "2023-08-30T21:24:57.103225Z"}], "thread_id": "Thread-4", "execution_time": 0.7130868434906006, "adapter_response": {}, "message": null, "failures": null, "unique_id": "model.apple_search_ads_source.stg_apple_search_ads__ad_history"}, {"status": "success", "timing": [{"name": "compile", "started_at": "2023-08-30T21:24:56.484404Z", "completed_at": "2023-08-30T21:24:57.195560Z"}, {"name": "execute", "started_at": "2023-08-30T21:24:57.204860Z", "completed_at": "2023-08-30T21:24:57.204864Z"}], "thread_id": "Thread-2", "execution_time": 0.7974748611450195, "adapter_response": {}, "message": null, "failures": null, "unique_id": "model.apple_search_ads_source.stg_apple_search_ads__ad_group_report"}, {"status": "success", "timing": [{"name": "compile", "started_at": "2023-08-30T21:24:56.477281Z", "completed_at": "2023-08-30T21:24:57.204078Z"}, {"name": "execute", "started_at": "2023-08-30T21:24:57.210905Z", "completed_at": "2023-08-30T21:24:57.210909Z"}], "thread_id": "Thread-7", "execution_time": 0.8067350387573242, "adapter_response": {}, "message": null, "failures": null, "unique_id": "model.apple_search_ads_source.stg_apple_search_ads__ad_group_history"}, {"status": "success", "timing": [{"name": "compile", "started_at": "2023-08-30T21:24:56.502509Z", "completed_at": "2023-08-30T21:24:57.176461Z"}, {"name": "execute", "started_at": "2023-08-30T21:24:57.201347Z", "completed_at": "2023-08-30T21:24:57.201355Z"}], "thread_id": "Thread-3", "execution_time": 0.7768800258636475, "adapter_response": {}, "message": null, "failures": null, "unique_id": "model.apple_search_ads_source.stg_apple_search_ads__campaign_report"}, {"status": "success", "timing": [{"name": "compile", "started_at": "2023-08-30T21:24:56.491719Z", "completed_at": "2023-08-30T21:24:57.204332Z"}, {"name": "execute", "started_at": "2023-08-30T21:24:57.211129Z", "completed_at": "2023-08-30T21:24:57.211133Z"}], "thread_id": "Thread-8", "execution_time": 0.8065097332000732, "adapter_response": {}, "message": null, "failures": null, "unique_id": "model.apple_search_ads_source.stg_apple_search_ads__campaign_history"}, {"status": "success", "timing": [{"name": "compile", "started_at": "2023-08-30T21:24:56.513900Z", "completed_at": "2023-08-30T21:24:57.202731Z"}, {"name": "execute", "started_at": "2023-08-30T21:24:57.206484Z", "completed_at": "2023-08-30T21:24:57.206488Z"}], "thread_id": "Thread-6", "execution_time": 0.7769608497619629, "adapter_response": {}, "message": null, "failures": null, "unique_id": "model.apple_search_ads_source.stg_apple_search_ads__keyword_report"}, {"status": "success", "timing": [{"name": "compile", "started_at": "2023-08-30T21:24:56.506297Z", "completed_at": "2023-08-30T21:24:57.190148Z"}, {"name": "execute", "started_at": "2023-08-30T21:24:57.204611Z", "completed_at": "2023-08-30T21:24:57.204617Z"}], "thread_id": "Thread-5", "execution_time": 0.7780418395996094, "adapter_response": {}, "message": null, "failures": null, "unique_id": "model.apple_search_ads_source.stg_apple_search_ads__keyword_history"}, {"status": "success", "timing": [{"name": "compile", "started_at": "2023-08-30T21:24:56.509917Z", "completed_at": "2023-08-30T21:24:57.203013Z"}, {"name": "execute", "started_at": "2023-08-30T21:24:57.206690Z", "completed_at": "2023-08-30T21:24:57.206694Z"}], "thread_id": "Thread-1", "execution_time": 0.7782430648803711, "adapter_response": {}, "message": null, "failures": null, "unique_id": "model.apple_search_ads_source.stg_apple_search_ads__ad_report"}, {"status": "success", "timing": [{"name": "compile", "started_at": "2023-08-30T21:24:57.298954Z", "completed_at": "2023-08-30T21:24:57.310496Z"}, {"name": "execute", "started_at": "2023-08-30T21:24:57.310937Z", "completed_at": "2023-08-30T21:24:57.310942Z"}], "thread_id": "Thread-8", "execution_time": 0.028526782989501953, "adapter_response": {}, "message": null, "failures": null, "unique_id": "test.apple_search_ads_source.not_null_stg_apple_search_ads__ad_history_modified_at.2eea7e006d"}, {"status": "success", "timing": [{"name": "compile", "started_at": "2023-08-30T21:24:57.291538Z", "completed_at": "2023-08-30T21:24:57.315575Z"}, {"name": "execute", "started_at": "2023-08-30T21:24:57.315967Z", "completed_at": "2023-08-30T21:24:57.315971Z"}], "thread_id": "Thread-3", "execution_time": 0.03418707847595215, "adapter_response": {}, "message": null, "failures": null, "unique_id": "test.apple_search_ads_source.not_null_stg_apple_search_ads__ad_history_ad_id.4ad3bde32a"}, {"status": "success", "timing": [{"name": "compile", "started_at": "2023-08-30T21:24:57.285194Z", "completed_at": "2023-08-30T21:24:57.316217Z"}, {"name": "execute", "started_at": "2023-08-30T21:24:57.318339Z", "completed_at": "2023-08-30T21:24:57.318342Z"}], "thread_id": "Thread-7", "execution_time": 0.037570953369140625, "adapter_response": {}, "message": null, "failures": null, "unique_id": "test.apple_search_ads_source.dbt_utils_unique_combination_of_columns_stg_apple_search_ads__ad_history_source_relation__ad_id__modified_at.45dfca7ca5"}, {"status": "success", "timing": [{"name": "compile", "started_at": "2023-08-30T21:24:57.312261Z", "completed_at": "2023-08-30T21:24:57.316915Z"}, {"name": "execute", "started_at": "2023-08-30T21:24:57.319334Z", "completed_at": "2023-08-30T21:24:57.319337Z"}], "thread_id": "Thread-8", "execution_time": 0.00905299186706543, "adapter_response": {}, "message": null, "failures": null, "unique_id": "test.apple_search_ads_source.dbt_utils_unique_combination_of_columns_stg_apple_search_ads__ad_group_history_source_relation__ad_group_id__modified_at.a6db663569"}, {"status": "success", "timing": [{"name": "compile", "started_at": "2023-08-30T21:24:57.301372Z", "completed_at": "2023-08-30T21:24:57.317308Z"}, {"name": "execute", "started_at": "2023-08-30T21:24:57.319934Z", "completed_at": "2023-08-30T21:24:57.319937Z"}], "thread_id": "Thread-6", "execution_time": 0.038359880447387695, "adapter_response": {}, "message": null, "failures": null, "unique_id": "test.apple_search_ads_source.dbt_utils_unique_combination_of_columns_stg_apple_search_ads__ad_group_report_source_relation__ad_group_id__date_day.dc4ccb902d"}, {"status": "success", "timing": [{"name": "compile", "started_at": "2023-08-30T21:24:57.307540Z", "completed_at": "2023-08-30T21:24:57.317533Z"}, {"name": "execute", "started_at": "2023-08-30T21:24:57.320150Z", "completed_at": "2023-08-30T21:24:57.320154Z"}], "thread_id": "Thread-1", "execution_time": 0.0381472110748291, "adapter_response": {}, "message": null, "failures": null, "unique_id": "test.apple_search_ads_source.not_null_stg_apple_search_ads__ad_group_report_date_day.4dfd46a43b"}, {"status": "success", "timing": [{"name": "compile", "started_at": "2023-08-30T21:24:57.304562Z", "completed_at": "2023-08-30T21:24:57.317964Z"}, {"name": "execute", "started_at": "2023-08-30T21:24:57.320514Z", "completed_at": "2023-08-30T21:24:57.320516Z"}], "thread_id": "Thread-5", "execution_time": 0.04137897491455078, "adapter_response": {}, "message": null, "failures": null, "unique_id": "test.apple_search_ads_source.not_null_stg_apple_search_ads__ad_group_report_ad_group_id.a115f9cfc1"}, {"status": "success", "timing": [{"name": "compile", "started_at": "2023-08-30T21:24:57.322145Z", "completed_at": "2023-08-30T21:24:57.327879Z"}, {"name": "execute", "started_at": "2023-08-30T21:24:57.342916Z", "completed_at": "2023-08-30T21:24:57.342922Z"}], "thread_id": "Thread-3", "execution_time": 0.025274038314819336, "adapter_response": {}, "message": null, "failures": null, "unique_id": "test.apple_search_ads_source.not_null_stg_apple_search_ads__ad_group_history_ad_group_id.dc128eecb7"}, {"status": "success", "timing": [{"name": "compile", "started_at": "2023-08-30T21:24:57.328096Z", "completed_at": "2023-08-30T21:24:57.343250Z"}, {"name": "execute", "started_at": "2023-08-30T21:24:57.345609Z", "completed_at": "2023-08-30T21:24:57.345612Z"}], "thread_id": "Thread-7", "execution_time": 0.02175283432006836, "adapter_response": {}, "message": null, "failures": null, "unique_id": "test.apple_search_ads_source.not_null_stg_apple_search_ads__ad_group_history_modified_at.e5d65fa28f"}, {"status": "success", "timing": [{"name": "compile", "started_at": "2023-08-30T21:24:57.334415Z", "completed_at": "2023-08-30T21:24:57.343497Z"}, {"name": "execute", "started_at": "2023-08-30T21:24:57.345825Z", "completed_at": "2023-08-30T21:24:57.345828Z"}], "thread_id": "Thread-6", "execution_time": 0.020705223083496094, "adapter_response": {}, "message": null, "failures": null, "unique_id": "test.apple_search_ads_source.not_null_stg_apple_search_ads__campaign_report_campaign_id.b83941e728"}, {"status": "success", "timing": [{"name": "compile", "started_at": "2023-08-30T21:24:57.330989Z", "completed_at": "2023-08-30T21:24:57.343747Z"}, {"name": "execute", "started_at": "2023-08-30T21:24:57.346196Z", "completed_at": "2023-08-30T21:24:57.346200Z"}], "thread_id": "Thread-8", "execution_time": 0.021839141845703125, "adapter_response": {}, "message": null, "failures": null, "unique_id": "test.apple_search_ads_source.dbt_utils_unique_combination_of_columns_stg_apple_search_ads__campaign_report_source_relation__campaign_id__date_day.87b6206f82"}, {"status": "success", "timing": [{"name": "compile", "started_at": "2023-08-30T21:24:57.337439Z", "completed_at": "2023-08-30T21:24:57.344814Z"}, {"name": "execute", "started_at": "2023-08-30T21:24:57.347779Z", "completed_at": "2023-08-30T21:24:57.347783Z"}], "thread_id": "Thread-1", "execution_time": 0.022371768951416016, "adapter_response": {}, "message": null, "failures": null, "unique_id": "test.apple_search_ads_source.not_null_stg_apple_search_ads__campaign_report_date_day.c8dc10a6f3"}, {"status": "success", "timing": [{"name": "compile", "started_at": "2023-08-30T21:24:57.339753Z", "completed_at": "2023-08-30T21:24:57.345177Z"}, {"name": "execute", "started_at": "2023-08-30T21:24:57.348439Z", "completed_at": "2023-08-30T21:24:57.348443Z"}], "thread_id": "Thread-5", "execution_time": 0.0226900577545166, "adapter_response": {}, "message": null, "failures": null, "unique_id": "test.apple_search_ads_source.dbt_utils_unique_combination_of_columns_stg_apple_search_ads__campaign_history_source_relation__campaign_id__modified_at.2e9f11582c"}, {"status": "success", "timing": [{"name": "compile", "started_at": "2023-08-30T21:24:57.350377Z", "completed_at": "2023-08-30T21:24:57.355224Z"}, {"name": "execute", "started_at": "2023-08-30T21:24:57.368106Z", "completed_at": "2023-08-30T21:24:57.368111Z"}], "thread_id": "Thread-3", "execution_time": 0.024904966354370117, "adapter_response": {}, "message": null, "failures": null, "unique_id": "test.apple_search_ads_source.not_null_stg_apple_search_ads__campaign_history_campaign_id.3f0f7502b8"}, {"status": "success", "timing": [{"name": "compile", "started_at": "2023-08-30T21:24:57.355706Z", "completed_at": "2023-08-30T21:24:57.368317Z"}, {"name": "execute", "started_at": "2023-08-30T21:24:57.373001Z", "completed_at": "2023-08-30T21:24:57.373004Z"}], "thread_id": "Thread-7", "execution_time": 0.021456003189086914, "adapter_response": {}, "message": null, "failures": null, "unique_id": "test.apple_search_ads_source.not_null_stg_apple_search_ads__campaign_history_modified_at.f34a7a97c9"}, {"status": "success", "timing": [{"name": "compile", "started_at": "2023-08-30T21:24:57.358115Z", "completed_at": "2023-08-30T21:24:57.370809Z"}, {"name": "execute", "started_at": "2023-08-30T21:24:57.373368Z", "completed_at": "2023-08-30T21:24:57.373371Z"}], "thread_id": "Thread-6", "execution_time": 0.02175593376159668, "adapter_response": {}, "message": null, "failures": null, "unique_id": "test.apple_search_ads_source.dbt_utils_unique_combination_of_columns_stg_apple_search_ads__keyword_history_source_relation__keyword_id__modified_at.635c0ce086"}, {"status": "success", "timing": [{"name": "compile", "started_at": "2023-08-30T21:24:57.361371Z", "completed_at": "2023-08-30T21:24:57.371077Z"}, {"name": "execute", "started_at": "2023-08-30T21:24:57.373569Z", "completed_at": "2023-08-30T21:24:57.373574Z"}], "thread_id": "Thread-8", "execution_time": 0.02161717414855957, "adapter_response": {}, "message": null, "failures": null, "unique_id": "test.apple_search_ads_source.dbt_utils_unique_combination_of_columns_stg_apple_search_ads__keyword_report_source_relation__keyword_id__date_day.855ae5524a"}, {"status": "success", "timing": [{"name": "compile", "started_at": "2023-08-30T21:24:57.365584Z", "completed_at": "2023-08-30T21:24:57.372001Z"}, {"name": "execute", "started_at": "2023-08-30T21:24:57.374662Z", "completed_at": "2023-08-30T21:24:57.374665Z"}], "thread_id": "Thread-1", "execution_time": 0.021672725677490234, "adapter_response": {}, "message": null, "failures": null, "unique_id": "test.apple_search_ads_source.not_null_stg_apple_search_ads__keyword_history_keyword_id.889f83cfd2"}, {"status": "success", "timing": [{"name": "compile", "started_at": "2023-08-30T21:24:57.368552Z", "completed_at": "2023-08-30T21:24:57.372779Z"}, {"name": "execute", "started_at": "2023-08-30T21:24:57.375847Z", "completed_at": "2023-08-30T21:24:57.375850Z"}], "thread_id": "Thread-5", "execution_time": 0.024250268936157227, "adapter_response": {}, "message": null, "failures": null, "unique_id": "test.apple_search_ads_source.not_null_stg_apple_search_ads__keyword_history_modified_at.42fde5a287"}, {"status": "success", "timing": [{"name": "compile", "started_at": "2023-08-30T21:24:57.377069Z", "completed_at": "2023-08-30T21:24:57.382014Z"}, {"name": "execute", "started_at": "2023-08-30T21:24:57.394338Z", "completed_at": "2023-08-30T21:24:57.394344Z"}], "thread_id": "Thread-3", "execution_time": 0.02407979965209961, "adapter_response": {}, "message": null, "failures": null, "unique_id": "test.apple_search_ads_source.not_null_stg_apple_search_ads__keyword_report_date_day.16098db928"}, {"status": "success", "timing": [{"name": "compile", "started_at": "2023-08-30T21:24:57.385206Z", "completed_at": "2023-08-30T21:24:57.396982Z"}, {"name": "execute", "started_at": "2023-08-30T21:24:57.399164Z", "completed_at": "2023-08-30T21:24:57.399168Z"}], "thread_id": "Thread-6", "execution_time": 0.019797086715698242, "adapter_response": {}, "message": null, "failures": null, "unique_id": "test.apple_search_ads_source.dbt_utils_unique_combination_of_columns_stg_apple_search_ads__ad_report_source_relation__ad_id__date_day__ad_group_id.f9bc5ff292"}, {"status": "success", "timing": [{"name": "compile", "started_at": "2023-08-30T21:24:57.382658Z", "completed_at": "2023-08-30T21:24:57.397207Z"}, {"name": "execute", "started_at": "2023-08-30T21:24:57.399567Z", "completed_at": "2023-08-30T21:24:57.399570Z"}], "thread_id": "Thread-7", "execution_time": 0.020954132080078125, "adapter_response": {}, "message": null, "failures": null, "unique_id": "test.apple_search_ads_source.not_null_stg_apple_search_ads__keyword_report_keyword_id.501725b09e"}, {"status": "success", "timing": [{"name": "compile", "started_at": "2023-08-30T21:24:57.388808Z", "completed_at": "2023-08-30T21:24:57.397476Z"}, {"name": "execute", "started_at": "2023-08-30T21:24:57.399769Z", "completed_at": "2023-08-30T21:24:57.399772Z"}], "thread_id": "Thread-8", "execution_time": 0.020522117614746094, "adapter_response": {}, "message": null, "failures": null, "unique_id": "test.apple_search_ads_source.not_null_stg_apple_search_ads__ad_report_ad_group_id.a397755e9f"}, {"status": "success", "timing": [{"name": "compile", "started_at": "2023-08-30T21:24:57.392008Z", "completed_at": "2023-08-30T21:24:57.398377Z"}, {"name": "execute", "started_at": "2023-08-30T21:24:57.400533Z", "completed_at": "2023-08-30T21:24:57.400536Z"}], "thread_id": "Thread-1", "execution_time": 0.02044510841369629, "adapter_response": {}, "message": null, "failures": null, "unique_id": "test.apple_search_ads_source.not_null_stg_apple_search_ads__ad_report_ad_id.d08e760c58"}, {"status": "success", "timing": [{"name": "compile", "started_at": "2023-08-30T21:24:57.394637Z", "completed_at": "2023-08-30T21:24:57.398901Z"}, {"name": "execute", "started_at": "2023-08-30T21:24:57.401551Z", "completed_at": "2023-08-30T21:24:57.401554Z"}], "thread_id": "Thread-5", "execution_time": 0.0200803279876709, "adapter_response": {}, "message": null, "failures": null, "unique_id": "test.apple_search_ads_source.not_null_stg_apple_search_ads__ad_report_date_day.e6252346d8"}, {"status": "success", "timing": [{"name": "compile", "started_at": "2023-08-30T21:24:57.206910Z", "completed_at": "2023-08-30T21:24:57.787302Z"}, {"name": "execute", "started_at": "2023-08-30T21:24:57.788182Z", "completed_at": "2023-08-30T21:24:57.788197Z"}], "thread_id": "Thread-4", "execution_time": 0.6513328552246094, "adapter_response": {}, "message": null, "failures": null, "unique_id": "model.apple_search_ads_source.stg_apple_search_ads__organization"}, {"status": "success", "timing": [{"name": "compile", "started_at": "2023-08-30T21:24:57.859893Z", "completed_at": "2023-08-30T21:24:57.868984Z"}, {"name": "execute", "started_at": "2023-08-30T21:24:57.869945Z", "completed_at": "2023-08-30T21:24:57.869949Z"}], "thread_id": "Thread-3", "execution_time": 0.01240396499633789, "adapter_response": {}, "message": null, "failures": null, "unique_id": "test.apple_search_ads_source.dbt_utils_unique_combination_of_columns_stg_apple_search_ads__organization_source_relation__organization_id.b5c488cb77"}, {"status": "success", "timing": [{"name": "compile", "started_at": "2023-08-30T21:24:57.864465Z", "completed_at": "2023-08-30T21:24:57.869245Z"}, {"name": "execute", "started_at": "2023-08-30T21:24:57.870210Z", "completed_at": "2023-08-30T21:24:57.870213Z"}], "thread_id": "Thread-6", "execution_time": 0.012411117553710938, "adapter_response": {}, "message": null, "failures": null, "unique_id": "test.apple_search_ads_source.not_null_stg_apple_search_ads__organization_organization_id.b013ce33cb"}, {"status": "success", "timing": [{"name": "compile", "started_at": "2023-08-30T21:24:57.271070Z", "completed_at": "2023-08-30T21:24:57.867782Z"}, {"name": "execute", "started_at": "2023-08-30T21:24:57.868395Z", "completed_at": "2023-08-30T21:24:57.868401Z"}], "thread_id": "Thread-2", "execution_time": 0.6468589305877686, "adapter_response": {}, "message": null, "failures": null, "unique_id": "model.apple_search_ads_source.stg_apple_search_ads__search_term_report"}, {"status": "success", "timing": [{"name": "compile", "started_at": "2023-08-30T21:24:57.919339Z", "completed_at": "2023-08-30T21:24:57.932016Z"}, {"name": "execute", "started_at": "2023-08-30T21:24:57.933249Z", "completed_at": "2023-08-30T21:24:57.933255Z"}], "thread_id": "Thread-8", "execution_time": 0.01695990562438965, "adapter_response": {}, "message": null, "failures": null, "unique_id": "test.apple_search_ads_source.dbt_utils_unique_combination_of_columns_stg_apple_search_ads__search_term_report_source_relation___fivetran_id__date_day.ef07562d98"}, {"status": "success", "timing": [{"name": "compile", "started_at": "2023-08-30T21:24:57.928677Z", "completed_at": "2023-08-30T21:24:57.932317Z"}, {"name": "execute", "started_at": "2023-08-30T21:24:57.933703Z", "completed_at": "2023-08-30T21:24:57.933706Z"}], "thread_id": "Thread-5", "execution_time": 0.016223907470703125, "adapter_response": {}, "message": null, "failures": null, "unique_id": "test.apple_search_ads_source.not_null_stg_apple_search_ads__search_term_report_date_day.fd93df3302"}, {"status": "success", "timing": [{"name": "compile", "started_at": "2023-08-30T21:24:57.925284Z", "completed_at": "2023-08-30T21:24:57.932790Z"}, {"name": "execute", "started_at": "2023-08-30T21:24:57.934482Z", "completed_at": "2023-08-30T21:24:57.934485Z"}], "thread_id": "Thread-1", "execution_time": 0.01751399040222168, "adapter_response": {}, "message": null, "failures": null, "unique_id": "test.apple_search_ads_source.not_null_stg_apple_search_ads__search_term_report__fivetran_id.aa430d1dad"}], "elapsed_time": 3.787432909011841, "args": {"indirect_selection": "eager", "log_format": "default", "select": [], "enable_legacy_logger": false, "exclude": [], "log_level": "info", "introspect": true, "use_colors": true, "vars": {}, "printer_width": 80, "defer": false, "profiles_dir": "/Users/catherinefritz/.dbt", "compile": true, "log_path": "/Users/catherinefritz/Documents/dbt_packages/apple_search_ads/dbt_apple_search_ads_source/integration_tests/logs", "write_json": true, "quiet": false, "send_anonymous_usage_stats": true, "print": true, "macro_debugging": false, "populate_cache": true, "favor_state": false, "warn_error_options": {"include": [], "exclude": []}, "strict_mode": false, "partial_parse": true, "static_parser": true, "use_colors_file": true, "cache_selected_only": false, "which": "generate", "project_dir": "/Users/catherinefritz/Documents/dbt_packages/apple_search_ads/dbt_apple_search_ads_source/integration_tests", "log_format_file": "debug", "version_check": true, "log_level_file": "debug"}}